MANIFEST.in
README.rst
setup.cfg
setup.py
version.py
src/cgcloud/__init__.py
src/cgcloud/core/__init__.py
src/cgcloud/core/agent_box.py
src/cgcloud/core/box.py
src/cgcloud/core/centos_box.py
src/cgcloud/core/cli.py
src/cgcloud/core/cloud_init_box.py
src/cgcloud/core/cluster.py
src/cgcloud/core/cluster_commands.py
src/cgcloud/core/commands.py
src/cgcloud/core/common_iam_policies.py
src/cgcloud/core/deprecated.py
src/cgcloud/core/docker_box.py
src/cgcloud/core/fedora_box.py
src/cgcloud/core/generic_boxes.py
src/cgcloud/core/init_box.py
src/cgcloud/core/instance_type.py
src/cgcloud/core/mesos_box.py
src/cgcloud/core/package_manager_box.py
src/cgcloud/core/project.py
src/cgcloud/core/rc_local_box.py
src/cgcloud/core/source_control_client.py
src/cgcloud/core/task.py
src/cgcloud/core/ubuntu_box.py
src/cgcloud/core/yum_box.py
src/cgcloud/fabric/__init__.py
src/cgcloud/fabric/operations.py
src/cgcloud_core.egg-info/PKG-INFO
src/cgcloud_core.egg-info/SOURCES.txt
src/cgcloud_core.egg-info/dependency_links.txt
src/cgcloud_core.egg-info/entry_points.txt
src/cgcloud_core.egg-info/namespace_packages.txt
src/cgcloud_core.egg-info/requires.txt
src/cgcloud_core.egg-info/top_level.txt