Metadata-Version: 1.0
Name: cgcloud-core
Version: 1.2.3
Summary: Efficient and reproducible software deployment for EC2 instances
Home-page: https://github.com/BD2KGenomics/cgcloud
Author: Hannes Schmidt
Author-email: hannes@ucsc.edu
License: UNKNOWN
Platform: UNKNOWN
